CHANGES.txt
buildout.cfg
ideas.txt
setup.py
src/hurry/__init__.py
src/hurry.custom.egg-info/PKG-INFO
src/hurry.custom.egg-info/SOURCES.txt
src/hurry.custom.egg-info/dependency_links.txt
src/hurry.custom.egg-info/namespace_packages.txt
src/hurry.custom.egg-info/not-zip-safe
src/hurry.custom.egg-info/requires.txt
src/hurry.custom.egg-info/top_level.txt
src/hurry/custom/README.txt
src/hurry/custom/__init__.py
src/hurry/custom/configure.zcml
src/hurry/custom/core.py
src/hurry/custom/interfaces.py
src/hurry/custom/jsont.py
src/hurry/custom/jsontemplate.txt
src/hurry/custom/meta.zcml
src/hurry/custom/testing.py
src/hurry/custom/tests.py
src/hurry/custom/zcml.py
src/hurry/custom/zcml.txt