Metadata-Version: 1.0
Name: hurry.custom
Version: 0.6.1
Summary: A framework for allowing customizing templates
Home-page: UNKNOWN
Author: Martijn Faassen, Startifact
Author-email: faassen@startifact.com
License: ZPL 2.1
Keywords: template custom templating customization
Platform: UNKNOWN
Classifier: Programming Language :: Python
Classifier: Topic :: Software Development :: Libraries :: Python Modules
